logquacious/__init__.py
logquacious/_compat.py
logquacious/backport_configurable_stacklevel.py
logquacious/cascading_config.py
logquacious/constants.py
logquacious/context_templates.py
logquacious/log_context.py
logquacious/log_manager.py
logquacious/utils.py
logquacious-0.5.0.dist-info/AUTHORS.rst
logquacious-0.5.0.dist-info/LICENSE
logquacious-0.5.0.dist-info/METADATA
logquacious-0.5.0.dist-info/WHEEL
logquacious-0.5.0.dist-info/top_level.txt
logquacious-0.5.0.dist-info/RECORD
